nbtester/__init__.py
nbtester/loader.py
nbtester-0.3.dist-info/METADATA
nbtester-0.3.dist-info/RECORD
nbtester-0.3.dist-info/WHEEL
nbtester-0.3.dist-info/top_level.txt
