Metadata-Version: 2.1
Name: nbtester
Version: 0.3
Summary: Test utilities for Jupyter Notebook file
Home-page: UNKNOWN
Author: Hiroki KIYOHARA
Author-email: hirokiky@gmail.com
License: UNKNOWN
Platform: UNKNOWN
Requires-Dist: nbformat
